kindle_download_helper/__init__.py
kindle_download_helper/__main__.py
kindle_download_helper/cli.py
kindle_download_helper/config.py
kindle_download_helper/kindle.py
kindle_download_helper/user_agents.py
kindle_download_helper/utils.py
kindle_download_helper/dedrm/__init__.py
kindle_download_helper/dedrm/k4mobidedrm.py
kindle_download_helper/dedrm/kgenpids.py
kindle_download_helper/dedrm/mobidedrm.py
kindle_download-1.4.0.dist-info/LICENSE
kindle_download-1.4.0.dist-info/METADATA
kindle_download-1.4.0.dist-info/WHEEL
kindle_download-1.4.0.dist-info/entry_points.txt
kindle_download-1.4.0.dist-info/top_level.txt
kindle_download-1.4.0.dist-info/RECORD
